py_leap_api/__init__.py
py_leap_api/leap.py
py_leap_api/utils.py
py_leap_api-0.0.6.dist-info/LICENSE
py_leap_api-0.0.6.dist-info/METADATA
py_leap_api-0.0.6.dist-info/WHEEL
py_leap_api-0.0.6.dist-info/top_level.txt
py_leap_api-0.0.6.dist-info/RECORD
