Metadata-Version: 2.1
Name: py-leap-api
Version: 0.0.6
Summary: Unofficial Library to interact with TryLeap REST API
Home-page: https://github.com/IperGiove/py_leap_api
Author: ipergiove
Author-email: ipergiove@duck.com
Project-URL: Doc, https://docs.tryleap.ai/reference/inferencescontroller_create-1
Project-URL: Source, https://github.com/IperGiove/py_leap_api
Keywords: Leap,api,genrative,image
Classifier: Development Status :: 5 - Production/Stable
Classifier: Intended Audience :: Developers
Classifier: Topic :: Software Development :: Build Tools
Classifier: License :: OSI Approved :: Apache Software License
Classifier: Programming Language :: Python :: 3.0
Classifier: Programming Language :: Python :: 3.2
Classifier: Programming Language :: Python :: 3.3
Classifier: Programming Language :: Python :: 3.4
Classifier: Programming Language :: Python :: 3.5
Classifier: Programming Language :: Python :: 3.6
Classifier: Programming Language :: Python :: 3.7
Classifier: Programming Language :: Python :: 3.8
Classifier: Programming Language :: Python :: 3.9
Requires-Python: >=3.0.0, <4
License-File: LICENSE
Requires-Dist: httpx (~=0.21.1)
